LICENCE
README.md
setup.py
statshelp/__init__.py
statshelp/statshelp.py
statshelp.egg-info/PKG-INFO
statshelp.egg-info/SOURCES.txt
statshelp.egg-info/dependency_links.txt
statshelp.egg-info/requires.txt
statshelp.egg-info/top_level.txt