Metadata-Version: 2.2
Name: statshelp
Version: 0.0.4
Summary: Library to help Data Science students
Author: Data Scientist
Author-email: datascientist@mateusalifontes.com
License: MIT License
Keywords: [stats,student,data science,analysis]
License-File: LICENCE
Requires-Dist: requests
Dynamic: author
Dynamic: author-email
Dynamic: description
Dynamic: description-content-type
Dynamic: keywords
Dynamic: license
Dynamic: requires-dist
Dynamic: summary
